timewarrior_extensions/__init__.py
timewarrior_extensions/install.py
timewarrior_extensions/percentage.py
timewarrior_extensions-0.1.1.dist-info/entry_points.txt
timewarrior_extensions-0.1.1.dist-info/LICENSE
timewarrior_extensions-0.1.1.dist-info/WHEEL
timewarrior_extensions-0.1.1.dist-info/METADATA
timewarrior_extensions-0.1.1.dist-info/RECORD
