Metadata-Version: 2.1
Name: timewarrior-extensions
Version: 0.1.1
Summary: Extensions for Timewarrior
Home-page: https://github.com/ViliamV/timewarrior-extensions
License: MIT
Keywords: timewarrior,timew,extensions
Author: Viliam Valent
Author-email: viliam@valent.email
Requires-Python: >=3.8
Classifier: License :: OSI Approved :: MIT License
Classifier: Programming Language :: Python :: 3
Classifier: Programming Language :: Python :: 3.8
Project-URL: Repository, https://github.com/ViliamV/timewarrior-extensions
